kontent_delivery/__init__.py
kontent_delivery/client.py
kontent_delivery/content_item.py
kontent_delivery/content_type.py
kontent_delivery/language.py
kontent_delivery/request_manager.py
kontent_delivery/taxonomy_group.py
kontent_delivery/builders/__init__.py
kontent_delivery/builders/content_builder.py
kontent_delivery/builders/filter_builder.py
kontent_delivery/builders/image_builder.py
kontent_delivery/builders/options_builder.py
kontent_delivery/builders/url_builder.py
kontent_delivery/resolvers/__init__.py
kontent_delivery/resolvers/content_link_resolver.py
kontent_delivery/resolvers/inline_item_resolver.py
kontent_delivery-0.1.3.dist-info/LICENSE
kontent_delivery-0.1.3.dist-info/METADATA
kontent_delivery-0.1.3.dist-info/WHEEL
kontent_delivery-0.1.3.dist-info/top_level.txt
kontent_delivery-0.1.3.dist-info/RECORD
